arytmetyka/__init__.py
arytmetyka/arth.py
game/__init__.py
game/main.py
ui/__init__.py
ui/main.py
ui/pokemon.png
ui/ui_check.py
super_projekt-0.0.3.dist-info/METADATA
super_projekt-0.0.3.dist-info/WHEEL
super_projekt-0.0.3.dist-info/top_level.txt
super_projekt-0.0.3.dist-info/RECORD
