Metadata-Version: 2.1
Name: super-projekt
Version: 0.0.3
Summary: super opis
Author: Gokuruto
Author-email: Gokuruto <gokuruto@gmail.com>
Classifier: Programming Language :: Python :: 3
Classifier: License :: OSI Approved :: MIT License
Classifier: Operating System :: OS Independent
Requires-Python: >=3.8
